{
	"Investments": [{
			"InvestmentID": "9001",
			"Name": "Digi Counsumer Business",
			"Cost": "14000000",
			"Target": "15000000",
			"TeamCount": "20",
			"MemberCount": "40",
			"HealthScore": "70",
			"Lead": "John Smith",
			"ParentID": null,
			"Sequence": "1",
			"Teams": [],
			"RoadMaps": []
		},
		{
			"InvestmentID": "9002",
			"Name": "Perdsonal Banking App",
			"Cost": "5200000",
			"Target": "4000000",
			"TeamCount": "12",
			"MemberCount": "90",
			"HealthScore": "30",
			"Lead": "Marie.G",
			"ParentID": "9001",
			"Details": {
				"Cost": "630000",
				"CostTarget": "800000",
				"CostHealth": "Healthy",
				"ActiveProgram": "V3.5 rollout",
				"Target": "March 2020",
				"ProgramHealth": "Needs Improvement",
				"BusinessValue": "78",
				"BusinessValueTarget": "100",
				"FytdCosts": {
					"CostType": "Development Program",
					"Actual": "2100000",
					"Budget": "3100000"
				}
			},
			"Teams": [{
					"TeamID": "3001",
					"TeamName": "Immortal Phoenix",
					"HeadCount": "7",
					"Productivity": "60",
					"Predictability": "67",
					"ProductOwner": "Jane Doe"
				},
				{
					"TeamID": "3002",
					"TeamName": "Digital Devils",
					"HeadCount": "11",
					"Productivity": "48",
					"Predictability": "78",
					"ProductOwner": "Grace Doe"
				}
			],
			"RoadMaps": [{
					"RoadmapItemId": "CLARITYTEST:roadmapItems:5009004",
					"Name": "Custom Inv Tasks & Assignment",
					"RoadmapID": "1001",
					"StartDate": "01/01/2020",
					"EndDate": "20/02/2020"

				},
				{
					"RoadmapItemId": "CLARITYTEST:roadmapItems:5009005",
					"Name": "Digital Product Mgt (Hierarchy)",
					"RoadmapID": "1001",
					"StartDate": "01/03/2020",
					"EndDate": "20/06/2020"
				},
				{
					"RoadmapItemId": "CLARITYTEST:roadmapItems:5009006",
					"Name": "Timeline improvements",
					"RoadmapID": "1001",
					"StartDate": "01/07/2020",
					"EndDate": "20/09/2020"
				},
				{
					"RoadmapItemId": "CLARITYTEST:roadmapItems:5009007",
					"Name": "MenuLinks",
					"RoadmapID": "1001",
					"StartDate": "01/10/2020",
					"EndDate": "20/12/2020"
				}
			]
		}, {
			"InvestmentID": "9003",
			"Name": "Modern Payment Systems",
			"Cost": "6300000",
			"Target": "8000000",
			"TeamCount": "4",
			"MemberCount": "27",
			"HealthScore": "89",
			"Lead": "Kiran.M",
			"ParentID": "9001",
			"Teams": [],
			"RoadMaps": []
		}
	],
	"RoadmapItem": {
		"RoadmapItemId": "CLARITYTEST:roadmapItems:5009004",
		"Portfolios": [{
				"PortfolioItemID": "RALLY:PORTFOLIOITEM:I5328",
				"PortfolioItemName": "Chat module development",
				"Score": 60,
				"Association": false
			},
			{
				"PortfolioItemID": "RALLY:PORTFOLIOITEM:I5329",
				"PortfolioItemName": "Virtual Assistant based on NLP",
				"Score": 80,
				"Association": false
			},
			{

				"PortfolioItemID": "RALLY:PORTFOLIOITEM:I5330",
				"PortfolioItemName": "Virtual Assistant for Mobile",
				"Score": 80,
				"Association": false
			},
			{

				"PortfolioItemID": "RALLY:PORTFOLIOITEM:I5332",
				"PortfolioItemName": "Virtual Assistant web interface",
				"Score": 70,
				"Association": false
			},
			{

				"PortfolioItemID": "RALLY:PORTFOLIOITEM:I4324",
				"PortfolioItemName": "Ability to save ticket creation form",
				"Score": 60,
				"Association": false
			},
			{

				"PortfolioItemID": "RALLY:PORTFOLIOITEM:I4345",
				"PortfolioItemName": "Ability to define sequence of attributes in ticket creation form",
				"Score": 40,
				"Association": false
			}
		],

		"Features": [{
				"FeatureID": "F89763",
				"Name": "Lorem Ipsum Dolor sit Amet",
				"Sate": "Development",
				"ReleaseTrain": "Digital Banking",
				"Cost": "103000",
				"CostEstimated": "150000",
				"PercentCompleted": "80",
				"PercentEstimated": "88",
				"Owner": "Jane Doe"

			},
			{
				"FeatureID": "F89770",
				"Name": "Lorem Ipsum Dolor sit Amet",
				"Sate": "Design",
				"ReleaseTrain": "Digital Banking",
				"Cost": "82000",
				"Cost_Estimated": "72000",
				"Cost_Predicted": "820000",
				"PercentCompleted": "28",
				"PercentEstimated": "64",
				"Owner": "John Doe"

			},
			{
				"FeatureID": "F89799",
				"Name": "Lorem Ipsum Dolor sit Amet",
				"Sate": "Development",
				"ReleaseTrain": "Digital Banking",
				"Cost": "90000",
				"Cost_Estimated": "140000",
				"Cost_Predicted": "130000",
				"PercentCompleted": "100",
				"PercentEstimated": "100",
				"Owner": "John Smith"

			},
			{
				"FeatureID": "F89774",
				"Name": "Lorem Ipsum Dolor sit Amet",
				"Sate": "Done",
				"ReleaseTrain": "Platform",
				"Cost": "88000",
				"Cost_Estimated": "138000",
				"Cost_Predicted": "135000",
				"PercentCompleted": "50",
				"PercentEstimated": "100",
				"Owner": "Grace Doe"
			}
		]
	}
}
